rrgcn/__init__.py
rrgcn/node_encoder.py
rrgcn/random_rgcn_conv.py
rrgcn/random_rgcn_embedder.py
rrgcn/util.py
rrgcn-0.0.2.dist-info/LICENSE
rrgcn-0.0.2.dist-info/METADATA
rrgcn-0.0.2.dist-info/WHEEL
rrgcn-0.0.2.dist-info/top_level.txt
rrgcn-0.0.2.dist-info/RECORD
