Metadata-Version: 2.1
Name: rrgcn
Version: 0.0.2
Summary: Random Relational Graph Convolutional Networks
Home-page: https://github.com/predict-idlab/RR-GCN
Author: Vic Degraeve
Author-email: vic.degraeve@ugent.be
License: UNKNOWN
Keywords: representation-learning,pytorch,knowledge-graph-embedding,random-relational-graph-convolutional-networks,relational-graph-convolutional-networks
Platform: UNKNOWN
Requires-Python: >=3.7
License-File: LICENSE
Requires-Dist: tqdm
Requires-Dist: numpy
Requires-Dist: scikit-learn
